everyaction/__init__.py
everyaction/client.py
everyaction/core.py
everyaction/exception.py
everyaction/objects.py
everyaction/services.py
everyaction_client-0.3.3.dist-info/LICENSE
everyaction_client-0.3.3.dist-info/METADATA
everyaction_client-0.3.3.dist-info/WHEEL
everyaction_client-0.3.3.dist-info/top_level.txt
everyaction_client-0.3.3.dist-info/RECORD
